moat/ems/inv/__init__.py
moat/ems/inv/_main.py
moat/ems/inv/_util.py
moat/ems/inv/analyze.py
moat/ems/inv/batt_current.py
moat/ems/inv/grid_power.py
moat/ems/inv/idle.py
moat/ems/inv/inv_power.py
moat/ems/inv/off.py
moat/ems/inv/remote.py
moat/ems/inv/set_soc.py
moat_ems_inv-0.2.13.dist-info/licenses/LICENSE.txt
moat_ems_inv-0.2.13.dist-info/METADATA
moat_ems_inv-0.2.13.dist-info/WHEEL
moat_ems_inv-0.2.13.dist-info/top_level.txt
moat_ems_inv-0.2.13.dist-info/RECORD
