Metadata-Version: 2.4
Name: moat-ems-inv
Version: 0.2.13
Summary: REPLACE ME
Author-email: Matthias Urlichs <matthias@urlichs.de>
Project-URL: homepage, https://m-o-a-t.org
Project-URL: repository, https://github.com/M-o-a-T/moat
Keywords: MoaT
Classifier: Development Status :: 4 - Beta
Classifier: Framework :: AnyIO
Classifier: Framework :: Trio
Classifier: Framework :: AsyncIO
Classifier: Programming Language :: Python :: 3
Classifier: Intended Audience :: Developers
Requires-Python: >=3.8
License-File: LICENSE.txt
Requires-Dist: anyio~=4.2
Requires-Dist: moat-util~=0.61.1
Requires-Dist: moat-modbus~=0.8.8
Requires-Dist: moat-lib-victron~=0.1.4
Dynamic: license-file
